{
	"id": "65b5bb89-da46-4309-8586-95674ed35d10",
	"name": "Variáveis",
	"values": [
		{
			"key": "Url\n",
			"value": "https://convergentes.qacoders-academy.com.br/",
			"type": "default",
			"enabled": true
		},
		{
			"key": "MailLoginAuth",
			"value": "sysadmin@qacoders.com",
			"type": "text",
			"enabled": true
		},
		{
			"key": "PasswordLoginAuth",
			"value": "1234@Test",
			"type": "secret",
			"enabled": true
		},
		{
			"key": "NOME_COMPOSTO",
			"value": "",
			"type": "default",
			"enabled": true
		},
		{
			"key": "CPF",
			"value": "",
			"type": "any",
			"enabled": true
		},
		{
			"key": "EMAIL",
			"value": "",
			"type": "any",
			"enabled": true
		},
		{
			"key": "USER_ID",
			"value": "",
			"type": "any",
			"enabled": true
		},
		{
			"key": "TokenProvider",
			"value": "",
			"type": "default",
			"enabled": true
		},
		{
			"key": "cnpj",
			"value": "",
			"type": "any",
			"enabled": true
		},
		{
			"key": "corporateName",
			"value": "",
			"type": "any",
			"enabled": true
		},
		{
			"key": "matriz",
			"value": "",
			"type": "any",
			"enabled": true
		},
		{
			"key": "empresaTeste",
			"value": "",
			"type": "any",
			"enabled": true
		}
	],
	"_postman_variable_scope": "environment",
	"_postman_exported_at": "2024-11-11T23:02:24.326Z",
	"_postman_exported_using": "Postman/11.19.0"
}